pyfastboot/__init__.py
pyfastboot/common.py
pyfastboot/common_cli.py
pyfastboot/fastboot.py
pyfastboot/fastboot_debug.py
pyfastboot/fastboot_extras.py
pyfastboot/usb_exceptions.py
pyfastboot-1.3.13.dist-info/licenses/LICENSE
pyfastboot-1.3.13.dist-info/METADATA
pyfastboot-1.3.13.dist-info/WHEEL
pyfastboot-1.3.13.dist-info/top_level.txt
pyfastboot-1.3.13.dist-info/RECORD
