Metadata-Version: 2.4
Name: pyfastboot
Version: 1.3.13
Summary: A pure python implementation of the Android Fastboot protocols
Home-page: https://github.com/HikariCalyx/python-fastboot
Author: Hikari Calyx
Author-email: Hikari Calyx <hikaricalyx@hikaricalyx.com>
Maintainer: Hikari Calyx
Maintainer-email: hikaricalyx@hikaricalyx.com
Project-URL: Homepage, https://github.com/HikariCalyx/python-fastboot
Project-URL: Issues, https://github.com/HikariCalyx/python-fastboot/issues
Classifier: Development Status :: 4 - Beta
Classifier: License :: OSI Approved :: Apache Software License
Classifier: Programming Language :: Python
Classifier: Programming Language :: Python :: 3
Classifier: Topic :: Software Development :: Testing
Requires-Python: >=3.8
License-File: LICENSE
Requires-Dist: libusb1>=1.0.16
Requires-Dist: progressbar>=2.3
Dynamic: author
Dynamic: home-page
Dynamic: license-file
Dynamic: maintainer
Dynamic: maintainer-email
